<?xml version="1.0" ?><YTMResult><ytm><category>Corporate Bond Ratings</category><Date>20100212</Date><ytm_details><profile_desc>A1 / A+</profile_desc><time_series_desc>3</time_series_desc><ytm>5.845</ytm></ytm_details><ytm_details><profile_desc>A1 / A+</profile_desc><time_series_desc>5</time_series_desc><ytm>6.434</ytm></ytm_details><ytm_details><profile_desc>A1 / A+</profile_desc><time_series_desc>7</time_series_desc><ytm>7.114</ytm></ytm_details><ytm_details><profile_desc>A1 / A+</profile_desc><time_series_desc>10</time_series_desc><ytm>7.991</ytm></ytm_details><ytm_details><profile_desc>A1 / A+</profile_desc><time_series_desc>15</time_series_desc><ytm>8.604</ytm></ytm_details><ytm_details><profile_desc>A2 / A</profile_desc><time_series_desc>3</time_series_desc><ytm>6.975</ytm></ytm_details><ytm_details><profile_desc>A2 / A</profile_desc><time_series_desc>5</time_series_desc><ytm>7.634</ytm></ytm_details><ytm_details><profile_desc>A2 / A</profile_desc><time_series_desc>7</time_series_desc><ytm>8.187</ytm></ytm_details><ytm_details><profile_desc>A2 / A</profile_desc><time_series_desc>10</time_series_desc><ytm>9.052</ytm></ytm_details><ytm_details><profile_desc>A2 / A</profile_desc><time_series_desc>15</time_series_desc><ytm>9.905</ytm></ytm_details><ytm_details><profile_desc>A3 / A-</profile_desc><time_series_desc>3</time_series_desc><ytm>7.917</ytm></ytm_details><ytm_details><profile_desc>A3 / A-</profile_desc><time_series_desc>5</time_series_desc><ytm>8.589</ytm></ytm_details><ytm_details><profile_desc>A3 / A-</profile_desc><time_series_desc>7</time_series_desc><ytm>9.293</ytm></ytm_details><ytm_details><profile_desc>A3 / A-</profile_desc><time_series_desc>10</time_series_desc><ytm>10.033</ytm></ytm_details><ytm_details><profile_desc>A3 / A-</profile_desc><time_series_desc>15</time_series_desc><ytm>11.027</ytm></ytm_details><ytm_details><profile_desc>AA1 / AA+</profile_desc><time_series_desc>3</time_series_desc><ytm>4.098</ytm></ytm_details><ytm_details><profile_desc>AA1 / AA+</profile_desc><time_series_desc>5</time_series_desc><ytm>4.695</ytm></ytm_details><ytm_details><profile_desc>AA1 / AA+</profile_desc><time_series_desc>7</time_series_desc><ytm>5.145</ytm></ytm_details><ytm_details><profile_desc>AA1 / AA+</profile_desc><time_series_desc>10</time_series_desc><ytm>5.662</ytm></ytm_details><ytm_details><profile_desc>AA1 / AA+</profile_desc><time_series_desc>15</time_series_desc><ytm>6.242</ytm></ytm_details><ytm_details><profile_desc>AA2 / AA</profile_desc><time_series_desc>3</time_series_desc><ytm>4.579</ytm></ytm_details><ytm_details><profile_desc>AA2 / AA</profile_desc><time_series_desc>5</time_series_desc><ytm>5.114</ytm></ytm_details><ytm_details><profile_desc>AA2 / AA</profile_desc><time_series_desc>7</time_series_desc><ytm>5.631</ytm></ytm_details><ytm_details><profile_desc>AA2 / AA</profile_desc><time_series_desc>10</time_series_desc><ytm>6.208</ytm></ytm_details><ytm_details><profile_desc>AA2 / AA</profile_desc><time_series_desc>15</time_series_desc><ytm>6.792</ytm></ytm_details><ytm_details><profile_desc>AA3 / AA-</profile_desc><time_series_desc>3</time_series_desc><ytm>5.028</ytm></ytm_details><ytm_details><profile_desc>AA3 / AA-</profile_desc><time_series_desc>5</time_series_desc><ytm>5.567</ytm></ytm_details><ytm_details><profile_desc>AA3 / AA-</profile_desc><time_series_desc>7</time_series_desc><ytm>6.038</ytm></ytm_details><ytm_details><profile_desc>AA3 / AA-</profile_desc><time_series_desc>10</time_series_desc><ytm>6.585</ytm></ytm_details><ytm_details><profile_desc>AA3 / AA-</profile_desc><time_series_desc>15</time_series_desc><ytm>7.423</ytm></ytm_details><ytm_details><profile_desc>AAA</profile_desc><time_series_desc>3</time_series_desc><ytm>3.737</ytm></ytm_details><ytm_details><profile_desc>AAA</profile_desc><time_series_desc>5</time_series_desc><ytm>4.298</ytm></ytm_details><ytm_details><profile_desc>AAA</profile_desc><time_series_desc>7</time_series_desc><ytm>4.748</ytm></ytm_details><ytm_details><profile_desc>AAA</profile_desc><time_series_desc>10</time_series_desc><ytm>5.263</ytm></ytm_details><ytm_details><profile_desc>AAA</profile_desc><time_series_desc>15</time_series_desc><ytm>5.712</ytm></ytm_details><ytm_details><profile_desc>BB &amp; BELOW</profile_desc><time_series_desc>3</time_series_desc><ytm>12.732</ytm></ytm_details><ytm_details><profile_desc>BB &amp; BELOW</profile_desc><time_series_desc>5</time_series_desc><ytm>14.277</ytm></ytm_details><ytm_details><profile_desc>BB &amp; BELOW</profile_desc><time_series_desc>7</time_series_desc><ytm>15.451</ytm></ytm_details><ytm_details><profile_desc>BB &amp; BELOW</profile_desc><time_series_desc>10</time_series_desc><ytm>16.730</ytm></ytm_details><ytm_details><profile_desc>BB &amp; BELOW</profile_desc><time_series_desc>15</time_series_desc><ytm>18.959</ytm></ytm_details><ytm_details><profile_desc>BBB</profile_desc><time_series_desc>3</time_series_desc><ytm>10.344</ytm></ytm_details><ytm_details><profile_desc>BBB</profile_desc><time_series_desc>5</time_series_desc><ytm>11.476</ytm></ytm_details><ytm_details><profile_desc>BBB</profile_desc><time_series_desc>7</time_series_desc><ytm>12.548</ytm></ytm_details><ytm_details><profile_desc>BBB</profile_desc><time_series_desc>10</time_series_desc><ytm>13.572</ytm></ytm_details><ytm_details><profile_desc>BBB</profile_desc><time_series_desc>15</time_series_desc><ytm>15.758</ytm></ytm_details></ytm></YTMResult>