<?xml version="1.0" ?><YTMResult><ytm><category>Corporate Bond Ratings</category><Date>20170721</Date><ytm_details><profile_desc>A1 / A+</profile_desc><time_series_desc>3</time_series_desc><ytm>5.177</ytm></ytm_details><ytm_details><profile_desc>A1 / A+</profile_desc><time_series_desc>5</time_series_desc><ytm>5.427</ytm></ytm_details><ytm_details><profile_desc>A1 / A+</profile_desc><time_series_desc>7</time_series_desc><ytm>5.796</ytm></ytm_details><ytm_details><profile_desc>A1 / A+</profile_desc><time_series_desc>10</time_series_desc><ytm>6.431</ytm></ytm_details><ytm_details><profile_desc>A1 / A+</profile_desc><time_series_desc>15</time_series_desc><ytm>7.208</ytm></ytm_details><ytm_details><profile_desc>A2 / A</profile_desc><time_series_desc>3</time_series_desc><ytm>6.062</ytm></ytm_details><ytm_details><profile_desc>A2 / A</profile_desc><time_series_desc>5</time_series_desc><ytm>6.624</ytm></ytm_details><ytm_details><profile_desc>A2 / A</profile_desc><time_series_desc>7</time_series_desc><ytm>7.123</ytm></ytm_details><ytm_details><profile_desc>A2 / A</profile_desc><time_series_desc>10</time_series_desc><ytm>8.070</ytm></ytm_details><ytm_details><profile_desc>A2 / A</profile_desc><time_series_desc>15</time_series_desc><ytm>8.938</ytm></ytm_details><ytm_details><profile_desc>A3 / A-</profile_desc><time_series_desc>3</time_series_desc><ytm>7.066</ytm></ytm_details><ytm_details><profile_desc>A3 / A-</profile_desc><time_series_desc>5</time_series_desc><ytm>7.921</ytm></ytm_details><ytm_details><profile_desc>A3 / A-</profile_desc><time_series_desc>7</time_series_desc><ytm>8.577</ytm></ytm_details><ytm_details><profile_desc>A3 / A-</profile_desc><time_series_desc>10</time_series_desc><ytm>9.472</ytm></ytm_details><ytm_details><profile_desc>A3 / A-</profile_desc><time_series_desc>15</time_series_desc><ytm>10.598</ytm></ytm_details><ytm_details><profile_desc>AA1 / AA+</profile_desc><time_series_desc>3</time_series_desc><ytm>4.299</ytm></ytm_details><ytm_details><profile_desc>AA1 / AA+</profile_desc><time_series_desc>5</time_series_desc><ytm>4.452</ytm></ytm_details><ytm_details><profile_desc>AA1 / AA+</profile_desc><time_series_desc>7</time_series_desc><ytm>4.608</ytm></ytm_details><ytm_details><profile_desc>AA1 / AA+</profile_desc><time_series_desc>10</time_series_desc><ytm>4.813</ytm></ytm_details><ytm_details><profile_desc>AA1 / AA+</profile_desc><time_series_desc>15</time_series_desc><ytm>5.149</ytm></ytm_details><ytm_details><profile_desc>AA2 / AA</profile_desc><time_series_desc>3</time_series_desc><ytm>4.475</ytm></ytm_details><ytm_details><profile_desc>AA2 / AA</profile_desc><time_series_desc>5</time_series_desc><ytm>4.648</ytm></ytm_details><ytm_details><profile_desc>AA2 / AA</profile_desc><time_series_desc>7</time_series_desc><ytm>4.799</ytm></ytm_details><ytm_details><profile_desc>AA2 / AA</profile_desc><time_series_desc>10</time_series_desc><ytm>5.010</ytm></ytm_details><ytm_details><profile_desc>AA2 / AA</profile_desc><time_series_desc>15</time_series_desc><ytm>5.344</ytm></ytm_details><ytm_details><profile_desc>AA3 / AA-</profile_desc><time_series_desc>3</time_series_desc><ytm>4.649</ytm></ytm_details><ytm_details><profile_desc>AA3 / AA-</profile_desc><time_series_desc>5</time_series_desc><ytm>4.816</ytm></ytm_details><ytm_details><profile_desc>AA3 / AA-</profile_desc><time_series_desc>7</time_series_desc><ytm>4.995</ytm></ytm_details><ytm_details><profile_desc>AA3 / AA-</profile_desc><time_series_desc>10</time_series_desc><ytm>5.219</ytm></ytm_details><ytm_details><profile_desc>AA3 / AA-</profile_desc><time_series_desc>15</time_series_desc><ytm>5.534</ytm></ytm_details><ytm_details><profile_desc>AAA</profile_desc><time_series_desc>3</time_series_desc><ytm>4.143</ytm></ytm_details><ytm_details><profile_desc>AAA</profile_desc><time_series_desc>5</time_series_desc><ytm>4.289</ytm></ytm_details><ytm_details><profile_desc>AAA</profile_desc><time_series_desc>7</time_series_desc><ytm>4.455</ytm></ytm_details><ytm_details><profile_desc>AAA</profile_desc><time_series_desc>10</time_series_desc><ytm>4.647</ytm></ytm_details><ytm_details><profile_desc>AAA</profile_desc><time_series_desc>15</time_series_desc><ytm>5.044</ytm></ytm_details><ytm_details><profile_desc>BB &amp; BELOW</profile_desc><time_series_desc>3</time_series_desc><ytm>11.016</ytm></ytm_details><ytm_details><profile_desc>BB &amp; BELOW</profile_desc><time_series_desc>5</time_series_desc><ytm>12.087</ytm></ytm_details><ytm_details><profile_desc>BB &amp; BELOW</profile_desc><time_series_desc>7</time_series_desc><ytm>13.154</ytm></ytm_details><ytm_details><profile_desc>BB &amp; BELOW</profile_desc><time_series_desc>10</time_series_desc><ytm>14.412</ytm></ytm_details><ytm_details><profile_desc>BB &amp; BELOW</profile_desc><time_series_desc>15</time_series_desc><ytm>15.936</ytm></ytm_details><ytm_details><profile_desc>BBB</profile_desc><time_series_desc>3</time_series_desc><ytm>8.933</ytm></ytm_details><ytm_details><profile_desc>BBB</profile_desc><time_series_desc>5</time_series_desc><ytm>9.928</ytm></ytm_details><ytm_details><profile_desc>BBB</profile_desc><time_series_desc>7</time_series_desc><ytm>10.734</ytm></ytm_details><ytm_details><profile_desc>BBB</profile_desc><time_series_desc>10</time_series_desc><ytm>11.933</ytm></ytm_details><ytm_details><profile_desc>BBB</profile_desc><time_series_desc>15</time_series_desc><ytm>13.355</ytm></ytm_details></ytm></YTMResult>