<?xml version="1.0" ?><YTMResult><ytm><category>Corporate Bond Selected Papers</category><Date>20210830</Date><ytm_details><profile_desc>CAGAMAS SECURITIES (NEW)</profile_desc><time_series_desc>3</time_series_desc><ytm>2.659</ytm></ytm_details><ytm_details><profile_desc>CAGAMAS SECURITIES (NEW)</profile_desc><time_series_desc>5</time_series_desc><ytm>3.014</ytm></ytm_details><ytm_details><profile_desc>CAGAMAS SECURITIES (NEW)</profile_desc><time_series_desc>7</time_series_desc><ytm>3.433</ytm></ytm_details><ytm_details><profile_desc>CAGAMAS SECURITIES (NEW)</profile_desc><time_series_desc>10</time_series_desc><ytm>3.725</ytm></ytm_details><ytm_details><profile_desc>CAGAMAS SECURITIES (OLD)</profile_desc><time_series_desc>3</time_series_desc><ytm>2.651</ytm></ytm_details><ytm_details><profile_desc>CAGAMAS SECURITIES (OLD)</profile_desc><time_series_desc>5</time_series_desc><ytm>3.010</ytm></ytm_details><ytm_details><profile_desc>CAGAMAS SECURITIES (OLD)</profile_desc><time_series_desc>7</time_series_desc><ytm>3.433</ytm></ytm_details><ytm_details><profile_desc>CAGAMAS SECURITIES (OLD)</profile_desc><time_series_desc>10</time_series_desc><ytm>3.725</ytm></ytm_details><ytm_details><profile_desc>KHAZANAH BOND</profile_desc><time_series_desc>3</time_series_desc><ytm>2.494</ytm></ytm_details><ytm_details><profile_desc>KHAZANAH BOND</profile_desc><time_series_desc>5</time_series_desc><ytm>2.831</ytm></ytm_details><ytm_details><profile_desc>KHAZANAH BOND</profile_desc><time_series_desc>7</time_series_desc><ytm>3.291</ytm></ytm_details><ytm_details><profile_desc>KHAZANAH BOND</profile_desc><time_series_desc>10</time_series_desc><ytm>3.631</ytm></ytm_details></ytm></YTMResult>