<?xml version="1.0" ?><YTMResult><ytm><category>Corporate Bond Selected Papers</category><Date>20200228</Date><ytm_details><profile_desc>CAGAMAS SECURITIES (NEW)</profile_desc><time_series_desc>3</time_series_desc><ytm>3.055</ytm></ytm_details><ytm_details><profile_desc>CAGAMAS SECURITIES (NEW)</profile_desc><time_series_desc>5</time_series_desc><ytm>3.166</ytm></ytm_details><ytm_details><profile_desc>CAGAMAS SECURITIES (NEW)</profile_desc><time_series_desc>7</time_series_desc><ytm>3.261</ytm></ytm_details><ytm_details><profile_desc>CAGAMAS SECURITIES (NEW)</profile_desc><time_series_desc>10</time_series_desc><ytm>3.356</ytm></ytm_details><ytm_details><profile_desc>CAGAMAS SECURITIES (OLD)</profile_desc><time_series_desc>3</time_series_desc><ytm>3.061</ytm></ytm_details><ytm_details><profile_desc>CAGAMAS SECURITIES (OLD)</profile_desc><time_series_desc>5</time_series_desc><ytm>3.173</ytm></ytm_details><ytm_details><profile_desc>CAGAMAS SECURITIES (OLD)</profile_desc><time_series_desc>7</time_series_desc><ytm>3.264</ytm></ytm_details><ytm_details><profile_desc>CAGAMAS SECURITIES (OLD)</profile_desc><time_series_desc>10</time_series_desc><ytm>3.357</ytm></ytm_details><ytm_details><profile_desc>KHAZANAH BOND</profile_desc><time_series_desc>3</time_series_desc><ytm>2.950</ytm></ytm_details><ytm_details><profile_desc>KHAZANAH BOND</profile_desc><time_series_desc>5</time_series_desc><ytm>3.104</ytm></ytm_details><ytm_details><profile_desc>KHAZANAH BOND</profile_desc><time_series_desc>7</time_series_desc><ytm>3.178</ytm></ytm_details><ytm_details><profile_desc>KHAZANAH BOND</profile_desc><time_series_desc>10</time_series_desc><ytm>3.294</ytm></ytm_details></ytm></YTMResult>