<?xml version="1.0" ?><YTMResult><ytm><category>Corporate Bond Ratings</category><Date>20111214</Date><ytm_details><profile_desc>A1 / A+</profile_desc><time_series_desc>3</time_series_desc><ytm>5.468</ytm></ytm_details><ytm_details><profile_desc>A1 / A+</profile_desc><time_series_desc>5</time_series_desc><ytm>6.032</ytm></ytm_details><ytm_details><profile_desc>A1 / A+</profile_desc><time_series_desc>7</time_series_desc><ytm>6.705</ytm></ytm_details><ytm_details><profile_desc>A1 / A+</profile_desc><time_series_desc>10</time_series_desc><ytm>7.455</ytm></ytm_details><ytm_details><profile_desc>A1 / A+</profile_desc><time_series_desc>15</time_series_desc><ytm>8.222</ytm></ytm_details><ytm_details><profile_desc>A2 / A</profile_desc><time_series_desc>3</time_series_desc><ytm>6.521</ytm></ytm_details><ytm_details><profile_desc>A2 / A</profile_desc><time_series_desc>5</time_series_desc><ytm>7.090</ytm></ytm_details><ytm_details><profile_desc>A2 / A</profile_desc><time_series_desc>7</time_series_desc><ytm>7.733</ytm></ytm_details><ytm_details><profile_desc>A2 / A</profile_desc><time_series_desc>10</time_series_desc><ytm>8.696</ytm></ytm_details><ytm_details><profile_desc>A2 / A</profile_desc><time_series_desc>15</time_series_desc><ytm>9.595</ytm></ytm_details><ytm_details><profile_desc>A3 / A-</profile_desc><time_series_desc>3</time_series_desc><ytm>7.567</ytm></ytm_details><ytm_details><profile_desc>A3 / A-</profile_desc><time_series_desc>5</time_series_desc><ytm>8.265</ytm></ytm_details><ytm_details><profile_desc>A3 / A-</profile_desc><time_series_desc>7</time_series_desc><ytm>8.986</ytm></ytm_details><ytm_details><profile_desc>A3 / A-</profile_desc><time_series_desc>10</time_series_desc><ytm>9.807</ytm></ytm_details><ytm_details><profile_desc>A3 / A-</profile_desc><time_series_desc>15</time_series_desc><ytm>10.880</ytm></ytm_details><ytm_details><profile_desc>AA1 / AA+</profile_desc><time_series_desc>3</time_series_desc><ytm>3.927</ytm></ytm_details><ytm_details><profile_desc>AA1 / AA+</profile_desc><time_series_desc>5</time_series_desc><ytm>4.269</ytm></ytm_details><ytm_details><profile_desc>AA1 / AA+</profile_desc><time_series_desc>7</time_series_desc><ytm>4.632</ytm></ytm_details><ytm_details><profile_desc>AA1 / AA+</profile_desc><time_series_desc>10</time_series_desc><ytm>5.094</ytm></ytm_details><ytm_details><profile_desc>AA1 / AA+</profile_desc><time_series_desc>15</time_series_desc><ytm>5.664</ytm></ytm_details><ytm_details><profile_desc>AA2 / AA</profile_desc><time_series_desc>3</time_series_desc><ytm>4.282</ytm></ytm_details><ytm_details><profile_desc>AA2 / AA</profile_desc><time_series_desc>5</time_series_desc><ytm>4.665</ytm></ytm_details><ytm_details><profile_desc>AA2 / AA</profile_desc><time_series_desc>7</time_series_desc><ytm>5.082</ytm></ytm_details><ytm_details><profile_desc>AA2 / AA</profile_desc><time_series_desc>10</time_series_desc><ytm>5.614</ytm></ytm_details><ytm_details><profile_desc>AA2 / AA</profile_desc><time_series_desc>15</time_series_desc><ytm>6.245</ytm></ytm_details><ytm_details><profile_desc>AA3 / AA-</profile_desc><time_series_desc>3</time_series_desc><ytm>4.534</ytm></ytm_details><ytm_details><profile_desc>AA3 / AA-</profile_desc><time_series_desc>5</time_series_desc><ytm>4.988</ytm></ytm_details><ytm_details><profile_desc>AA3 / AA-</profile_desc><time_series_desc>7</time_series_desc><ytm>5.423</ytm></ytm_details><ytm_details><profile_desc>AA3 / AA-</profile_desc><time_series_desc>10</time_series_desc><ytm>5.945</ytm></ytm_details><ytm_details><profile_desc>AA3 / AA-</profile_desc><time_series_desc>15</time_series_desc><ytm>6.882</ytm></ytm_details><ytm_details><profile_desc>AAA</profile_desc><time_series_desc>3</time_series_desc><ytm>3.639</ytm></ytm_details><ytm_details><profile_desc>AAA</profile_desc><time_series_desc>5</time_series_desc><ytm>4.002</ytm></ytm_details><ytm_details><profile_desc>AAA</profile_desc><time_series_desc>7</time_series_desc><ytm>4.328</ytm></ytm_details><ytm_details><profile_desc>AAA</profile_desc><time_series_desc>10</time_series_desc><ytm>4.691</ytm></ytm_details><ytm_details><profile_desc>AAA</profile_desc><time_series_desc>15</time_series_desc><ytm>5.134</ytm></ytm_details><ytm_details><profile_desc>BB &amp; BELOW</profile_desc><time_series_desc>3</time_series_desc><ytm>12.607</ytm></ytm_details><ytm_details><profile_desc>BB &amp; BELOW</profile_desc><time_series_desc>5</time_series_desc><ytm>14.070</ytm></ytm_details><ytm_details><profile_desc>BB &amp; BELOW</profile_desc><time_series_desc>7</time_series_desc><ytm>15.157</ytm></ytm_details><ytm_details><profile_desc>BB &amp; BELOW</profile_desc><time_series_desc>10</time_series_desc><ytm>16.308</ytm></ytm_details><ytm_details><profile_desc>BB &amp; BELOW</profile_desc><time_series_desc>15</time_series_desc><ytm>18.667</ytm></ytm_details><ytm_details><profile_desc>BBB</profile_desc><time_series_desc>3</time_series_desc><ytm>10.158</ytm></ytm_details><ytm_details><profile_desc>BBB</profile_desc><time_series_desc>5</time_series_desc><ytm>11.211</ytm></ytm_details><ytm_details><profile_desc>BBB</profile_desc><time_series_desc>7</time_series_desc><ytm>12.343</ytm></ytm_details><ytm_details><profile_desc>BBB</profile_desc><time_series_desc>10</time_series_desc><ytm>13.672</ytm></ytm_details><ytm_details><profile_desc>BBB</profile_desc><time_series_desc>15</time_series_desc><ytm>15.662</ytm></ytm_details></ytm></YTMResult>