<?xml version="1.0" ?><YTMResult><ytm><category>Corporate Bond Ratings</category><Date>20170630</Date><ytm_details><profile_desc>A1 / A+</profile_desc><time_series_desc>3</time_series_desc><ytm>5.144</ytm></ytm_details><ytm_details><profile_desc>A1 / A+</profile_desc><time_series_desc>5</time_series_desc><ytm>5.402</ytm></ytm_details><ytm_details><profile_desc>A1 / A+</profile_desc><time_series_desc>7</time_series_desc><ytm>5.771</ytm></ytm_details><ytm_details><profile_desc>A1 / A+</profile_desc><time_series_desc>10</time_series_desc><ytm>6.389</ytm></ytm_details><ytm_details><profile_desc>A1 / A+</profile_desc><time_series_desc>15</time_series_desc><ytm>7.122</ytm></ytm_details><ytm_details><profile_desc>A2 / A</profile_desc><time_series_desc>3</time_series_desc><ytm>5.968</ytm></ytm_details><ytm_details><profile_desc>A2 / A</profile_desc><time_series_desc>5</time_series_desc><ytm>6.526</ytm></ytm_details><ytm_details><profile_desc>A2 / A</profile_desc><time_series_desc>7</time_series_desc><ytm>7.056</ytm></ytm_details><ytm_details><profile_desc>A2 / A</profile_desc><time_series_desc>10</time_series_desc><ytm>8.015</ytm></ytm_details><ytm_details><profile_desc>A2 / A</profile_desc><time_series_desc>15</time_series_desc><ytm>8.850</ytm></ytm_details><ytm_details><profile_desc>A3 / A-</profile_desc><time_series_desc>3</time_series_desc><ytm>6.959</ytm></ytm_details><ytm_details><profile_desc>A3 / A-</profile_desc><time_series_desc>5</time_series_desc><ytm>7.816</ytm></ytm_details><ytm_details><profile_desc>A3 / A-</profile_desc><time_series_desc>7</time_series_desc><ytm>8.467</ytm></ytm_details><ytm_details><profile_desc>A3 / A-</profile_desc><time_series_desc>10</time_series_desc><ytm>9.350</ytm></ytm_details><ytm_details><profile_desc>A3 / A-</profile_desc><time_series_desc>15</time_series_desc><ytm>10.479</ytm></ytm_details><ytm_details><profile_desc>AA1 / AA+</profile_desc><time_series_desc>3</time_series_desc><ytm>4.293</ytm></ytm_details><ytm_details><profile_desc>AA1 / AA+</profile_desc><time_series_desc>5</time_series_desc><ytm>4.452</ytm></ytm_details><ytm_details><profile_desc>AA1 / AA+</profile_desc><time_series_desc>7</time_series_desc><ytm>4.617</ytm></ytm_details><ytm_details><profile_desc>AA1 / AA+</profile_desc><time_series_desc>10</time_series_desc><ytm>4.814</ytm></ytm_details><ytm_details><profile_desc>AA1 / AA+</profile_desc><time_series_desc>15</time_series_desc><ytm>5.152</ytm></ytm_details><ytm_details><profile_desc>AA2 / AA</profile_desc><time_series_desc>3</time_series_desc><ytm>4.456</ytm></ytm_details><ytm_details><profile_desc>AA2 / AA</profile_desc><time_series_desc>5</time_series_desc><ytm>4.638</ytm></ytm_details><ytm_details><profile_desc>AA2 / AA</profile_desc><time_series_desc>7</time_series_desc><ytm>4.810</ytm></ytm_details><ytm_details><profile_desc>AA2 / AA</profile_desc><time_series_desc>10</time_series_desc><ytm>5.015</ytm></ytm_details><ytm_details><profile_desc>AA2 / AA</profile_desc><time_series_desc>15</time_series_desc><ytm>5.351</ytm></ytm_details><ytm_details><profile_desc>AA3 / AA-</profile_desc><time_series_desc>3</time_series_desc><ytm>4.630</ytm></ytm_details><ytm_details><profile_desc>AA3 / AA-</profile_desc><time_series_desc>5</time_series_desc><ytm>4.807</ytm></ytm_details><ytm_details><profile_desc>AA3 / AA-</profile_desc><time_series_desc>7</time_series_desc><ytm>5.005</ytm></ytm_details><ytm_details><profile_desc>AA3 / AA-</profile_desc><time_series_desc>10</time_series_desc><ytm>5.226</ytm></ytm_details><ytm_details><profile_desc>AA3 / AA-</profile_desc><time_series_desc>15</time_series_desc><ytm>5.545</ytm></ytm_details><ytm_details><profile_desc>AAA</profile_desc><time_series_desc>3</time_series_desc><ytm>4.140</ytm></ytm_details><ytm_details><profile_desc>AAA</profile_desc><time_series_desc>5</time_series_desc><ytm>4.295</ytm></ytm_details><ytm_details><profile_desc>AAA</profile_desc><time_series_desc>7</time_series_desc><ytm>4.458</ytm></ytm_details><ytm_details><profile_desc>AAA</profile_desc><time_series_desc>10</time_series_desc><ytm>4.653</ytm></ytm_details><ytm_details><profile_desc>AAA</profile_desc><time_series_desc>15</time_series_desc><ytm>5.031</ytm></ytm_details><ytm_details><profile_desc>BB &amp; BELOW</profile_desc><time_series_desc>3</time_series_desc><ytm>10.936</ytm></ytm_details><ytm_details><profile_desc>BB &amp; BELOW</profile_desc><time_series_desc>5</time_series_desc><ytm>12.019</ytm></ytm_details><ytm_details><profile_desc>BB &amp; BELOW</profile_desc><time_series_desc>7</time_series_desc><ytm>13.085</ytm></ytm_details><ytm_details><profile_desc>BB &amp; BELOW</profile_desc><time_series_desc>10</time_series_desc><ytm>14.355</ytm></ytm_details><ytm_details><profile_desc>BB &amp; BELOW</profile_desc><time_series_desc>15</time_series_desc><ytm>15.806</ytm></ytm_details><ytm_details><profile_desc>BBB</profile_desc><time_series_desc>3</time_series_desc><ytm>8.762</ytm></ytm_details><ytm_details><profile_desc>BBB</profile_desc><time_series_desc>5</time_series_desc><ytm>9.775</ytm></ytm_details><ytm_details><profile_desc>BBB</profile_desc><time_series_desc>7</time_series_desc><ytm>10.566</ytm></ytm_details><ytm_details><profile_desc>BBB</profile_desc><time_series_desc>10</time_series_desc><ytm>11.774</ytm></ytm_details><ytm_details><profile_desc>BBB</profile_desc><time_series_desc>15</time_series_desc><ytm>13.125</ytm></ytm_details></ytm></YTMResult>