<?xml version="1.0" ?><YTMResult><ytm><category>Corporate Bond Selected Papers</category><Date>20200407</Date><ytm_details><profile_desc>CAGAMAS SECURITIES (NEW)</profile_desc><time_series_desc>3</time_series_desc><ytm>3.382</ytm></ytm_details><ytm_details><profile_desc>CAGAMAS SECURITIES (NEW)</profile_desc><time_series_desc>5</time_series_desc><ytm>3.593</ytm></ytm_details><ytm_details><profile_desc>CAGAMAS SECURITIES (NEW)</profile_desc><time_series_desc>7</time_series_desc><ytm>3.812</ytm></ytm_details><ytm_details><profile_desc>CAGAMAS SECURITIES (NEW)</profile_desc><time_series_desc>10</time_series_desc><ytm>3.957</ytm></ytm_details><ytm_details><profile_desc>CAGAMAS SECURITIES (OLD)</profile_desc><time_series_desc>3</time_series_desc><ytm>3.375</ytm></ytm_details><ytm_details><profile_desc>CAGAMAS SECURITIES (OLD)</profile_desc><time_series_desc>5</time_series_desc><ytm>3.586</ytm></ytm_details><ytm_details><profile_desc>CAGAMAS SECURITIES (OLD)</profile_desc><time_series_desc>7</time_series_desc><ytm>3.811</ytm></ytm_details><ytm_details><profile_desc>CAGAMAS SECURITIES (OLD)</profile_desc><time_series_desc>10</time_series_desc><ytm>3.948</ytm></ytm_details><ytm_details><profile_desc>KHAZANAH BOND</profile_desc><time_series_desc>3</time_series_desc><ytm>3.328</ytm></ytm_details><ytm_details><profile_desc>KHAZANAH BOND</profile_desc><time_series_desc>5</time_series_desc><ytm>3.492</ytm></ytm_details><ytm_details><profile_desc>KHAZANAH BOND</profile_desc><time_series_desc>7</time_series_desc><ytm>3.692</ytm></ytm_details><ytm_details><profile_desc>KHAZANAH BOND</profile_desc><time_series_desc>10</time_series_desc><ytm>3.818</ytm></ytm_details></ytm></YTMResult>