<?xml version="1.0" ?><YTMResult><ytm><category>Corporate Bond Ratings</category><Date>20230731</Date><ytm_details><profile_desc>A1 / A+</profile_desc><time_series_desc>3</time_series_desc><ytm>4.744</ytm></ytm_details><ytm_details><profile_desc>A1 / A+</profile_desc><time_series_desc>5</time_series_desc><ytm>4.927</ytm></ytm_details><ytm_details><profile_desc>A1 / A+</profile_desc><time_series_desc>7</time_series_desc><ytm>5.091</ytm></ytm_details><ytm_details><profile_desc>A1 / A+</profile_desc><time_series_desc>10</time_series_desc><ytm>5.277</ytm></ytm_details><ytm_details><profile_desc>A1 / A+</profile_desc><time_series_desc>15</time_series_desc><ytm>5.637</ytm></ytm_details><ytm_details><profile_desc>A2 / A</profile_desc><time_series_desc>3</time_series_desc><ytm>5.281</ytm></ytm_details><ytm_details><profile_desc>A2 / A</profile_desc><time_series_desc>5</time_series_desc><ytm>5.599</ytm></ytm_details><ytm_details><profile_desc>A2 / A</profile_desc><time_series_desc>7</time_series_desc><ytm>5.826</ytm></ytm_details><ytm_details><profile_desc>A2 / A</profile_desc><time_series_desc>10</time_series_desc><ytm>6.082</ytm></ytm_details><ytm_details><profile_desc>A2 / A</profile_desc><time_series_desc>15</time_series_desc><ytm>6.528</ytm></ytm_details><ytm_details><profile_desc>A3 / A-</profile_desc><time_series_desc>3</time_series_desc><ytm>5.829</ytm></ytm_details><ytm_details><profile_desc>A3 / A-</profile_desc><time_series_desc>5</time_series_desc><ytm>6.136</ytm></ytm_details><ytm_details><profile_desc>A3 / A-</profile_desc><time_series_desc>7</time_series_desc><ytm>6.403</ytm></ytm_details><ytm_details><profile_desc>A3 / A-</profile_desc><time_series_desc>10</time_series_desc><ytm>6.789</ytm></ytm_details><ytm_details><profile_desc>A3 / A-</profile_desc><time_series_desc>15</time_series_desc><ytm>7.584</ytm></ytm_details><ytm_details><profile_desc>AA1 / AA+</profile_desc><time_series_desc>3</time_series_desc><ytm>4.041</ytm></ytm_details><ytm_details><profile_desc>AA1 / AA+</profile_desc><time_series_desc>5</time_series_desc><ytm>4.180</ytm></ytm_details><ytm_details><profile_desc>AA1 / AA+</profile_desc><time_series_desc>7</time_series_desc><ytm>4.294</ytm></ytm_details><ytm_details><profile_desc>AA1 / AA+</profile_desc><time_series_desc>10</time_series_desc><ytm>4.422</ytm></ytm_details><ytm_details><profile_desc>AA1 / AA+</profile_desc><time_series_desc>15</time_series_desc><ytm>4.598</ytm></ytm_details><ytm_details><profile_desc>AA2 / AA</profile_desc><time_series_desc>3</time_series_desc><ytm>4.139</ytm></ytm_details><ytm_details><profile_desc>AA2 / AA</profile_desc><time_series_desc>5</time_series_desc><ytm>4.296</ytm></ytm_details><ytm_details><profile_desc>AA2 / AA</profile_desc><time_series_desc>7</time_series_desc><ytm>4.399</ytm></ytm_details><ytm_details><profile_desc>AA2 / AA</profile_desc><time_series_desc>10</time_series_desc><ytm>4.553</ytm></ytm_details><ytm_details><profile_desc>AA2 / AA</profile_desc><time_series_desc>15</time_series_desc><ytm>4.764</ytm></ytm_details><ytm_details><profile_desc>AA3 / AA-</profile_desc><time_series_desc>3</time_series_desc><ytm>4.291</ytm></ytm_details><ytm_details><profile_desc>AA3 / AA-</profile_desc><time_series_desc>5</time_series_desc><ytm>4.477</ytm></ytm_details><ytm_details><profile_desc>AA3 / AA-</profile_desc><time_series_desc>7</time_series_desc><ytm>4.579</ytm></ytm_details><ytm_details><profile_desc>AA3 / AA-</profile_desc><time_series_desc>10</time_series_desc><ytm>4.717</ytm></ytm_details><ytm_details><profile_desc>AA3 / AA-</profile_desc><time_series_desc>15</time_series_desc><ytm>5.008</ytm></ytm_details><ytm_details><profile_desc>AAA</profile_desc><time_series_desc>3</time_series_desc><ytm>3.943</ytm></ytm_details><ytm_details><profile_desc>AAA</profile_desc><time_series_desc>5</time_series_desc><ytm>4.084</ytm></ytm_details><ytm_details><profile_desc>AAA</profile_desc><time_series_desc>7</time_series_desc><ytm>4.192</ytm></ytm_details><ytm_details><profile_desc>AAA</profile_desc><time_series_desc>10</time_series_desc><ytm>4.286</ytm></ytm_details><ytm_details><profile_desc>AAA</profile_desc><time_series_desc>15</time_series_desc><ytm>4.423</ytm></ytm_details><ytm_details><profile_desc>BB &amp; BELOW</profile_desc><time_series_desc>3</time_series_desc><ytm>8.541</ytm></ytm_details><ytm_details><profile_desc>BB &amp; BELOW</profile_desc><time_series_desc>5</time_series_desc><ytm>9.608</ytm></ytm_details><ytm_details><profile_desc>BB &amp; BELOW</profile_desc><time_series_desc>7</time_series_desc><ytm>10.463</ytm></ytm_details><ytm_details><profile_desc>BB &amp; BELOW</profile_desc><time_series_desc>10</time_series_desc><ytm>11.314</ytm></ytm_details><ytm_details><profile_desc>BB &amp; BELOW</profile_desc><time_series_desc>15</time_series_desc><ytm>12.564</ytm></ytm_details><ytm_details><profile_desc>BBB</profile_desc><time_series_desc>3</time_series_desc><ytm>6.674</ytm></ytm_details><ytm_details><profile_desc>BBB</profile_desc><time_series_desc>5</time_series_desc><ytm>7.013</ytm></ytm_details><ytm_details><profile_desc>BBB</profile_desc><time_series_desc>7</time_series_desc><ytm>7.511</ytm></ytm_details><ytm_details><profile_desc>BBB</profile_desc><time_series_desc>10</time_series_desc><ytm>7.986</ytm></ytm_details><ytm_details><profile_desc>BBB</profile_desc><time_series_desc>15</time_series_desc><ytm>8.997</ytm></ytm_details></ytm></YTMResult>