<?xml version="1.0" ?><YTMResult><ytm><category>Government Securities (Conventional) New</category><Date>20160526</Date><ytm_details><profile_desc>BNMN</profile_desc><time_series_desc>Time series - BAND 1</time_series_desc><ytm>2.785</ytm></ytm_details><ytm_details><profile_desc>BNMN</profile_desc><time_series_desc>Time series - BAND 10</time_series_desc><ytm>2.867</ytm></ytm_details><ytm_details><profile_desc>BNMN</profile_desc><time_series_desc>Time series - BAND 4</time_series_desc><ytm>2.797</ytm></ytm_details><ytm_details><profile_desc>BNMN</profile_desc><time_series_desc>Time series - BAND 7</time_series_desc><ytm>2.832</ytm></ytm_details><ytm_details><profile_desc>mgs</profile_desc><time_series_desc>Time series - 1 YEAR</time_series_desc><ytm>2.932</ytm></ytm_details><ytm_details><profile_desc>MGS</profile_desc><time_series_desc>Time series - 2 YEARS</time_series_desc><ytm>2.997</ytm></ytm_details><ytm_details><profile_desc>MGS</profile_desc><time_series_desc>Time series - 3 YEARS</time_series_desc><ytm>3.263</ytm></ytm_details><ytm_details><profile_desc>MGS</profile_desc><time_series_desc>Time series - 4 YEARS</time_series_desc><ytm>3.395</ytm></ytm_details><ytm_details><profile_desc>MGS</profile_desc><time_series_desc>Time series - 5 YEARS</time_series_desc><ytm>3.492</ytm></ytm_details><ytm_details><profile_desc>MGS</profile_desc><time_series_desc>Time series - 6 YEARS</time_series_desc><ytm>3.636</ytm></ytm_details><ytm_details><profile_desc>MGS</profile_desc><time_series_desc>Time series - 7 YEARS</time_series_desc><ytm>3.800</ytm></ytm_details><ytm_details><profile_desc>MGS</profile_desc><time_series_desc>Time series - 8 YEARS</time_series_desc><ytm>3.831</ytm></ytm_details><ytm_details><profile_desc>MGS</profile_desc><time_series_desc>Time series - 9 YEARS</time_series_desc><ytm>3.866</ytm></ytm_details><ytm_details><profile_desc>MGS</profile_desc><time_series_desc>Time series - 10 YEARS</time_series_desc><ytm>3.900</ytm></ytm_details><ytm_details><profile_desc>MGS</profile_desc><time_series_desc>Time series - 15 YEARS</time_series_desc><ytm>4.181</ytm></ytm_details><ytm_details><profile_desc>MGS</profile_desc><time_series_desc>Time series - 20 YEARS</time_series_desc><ytm>4.297</ytm></ytm_details><ytm_details><profile_desc>MGS</profile_desc><time_series_desc>Time series - 30 YEARS</time_series_desc><ytm>4.674</ytm></ytm_details><ytm_details><profile_desc>MTB</profile_desc><time_series_desc>Time series - BAND 1</time_series_desc><ytm>2.792</ytm></ytm_details><ytm_details><profile_desc>MTB</profile_desc><time_series_desc>Time series - BAND 10</time_series_desc><ytm>2.875</ytm></ytm_details><ytm_details><profile_desc>MTB</profile_desc><time_series_desc>Time series - BAND 4</time_series_desc><ytm>2.805</ytm></ytm_details><ytm_details><profile_desc>MTB</profile_desc><time_series_desc>Time series - BAND 7</time_series_desc><ytm>2.839</ytm></ytm_details></ytm></YTMResult>