<?xml version="1.0" ?><YTMResult><ytm><category>Government Securities (Islamic) New</category><Date>20200310</Date><ytm_details><profile_desc>BNMNI</profile_desc><time_series_desc>Time series - BAND 1</time_series_desc><ytm>2.540</ytm></ytm_details><ytm_details><profile_desc>BNMNI</profile_desc><time_series_desc>Time series - BAND 10</time_series_desc><ytm>2.596</ytm></ytm_details><ytm_details><profile_desc>BNMNI</profile_desc><time_series_desc>Time series - BAND 4</time_series_desc><ytm>2.544</ytm></ytm_details><ytm_details><profile_desc>BNMNI</profile_desc><time_series_desc>Time series - BAND 7</time_series_desc><ytm>2.562</ytm></ytm_details><ytm_details><profile_desc>GII</profile_desc><time_series_desc>Time series - 1 YEAR</time_series_desc><ytm>2.578</ytm></ytm_details><ytm_details><profile_desc>GII</profile_desc><time_series_desc>Time series - 2 YEARS</time_series_desc><ytm>2.609</ytm></ytm_details><ytm_details><profile_desc>GII</profile_desc><time_series_desc>Time series - 3 YEARS</time_series_desc><ytm>2.641</ytm></ytm_details><ytm_details><profile_desc>GII</profile_desc><time_series_desc>Time series - 4 YEARS</time_series_desc><ytm>2.674</ytm></ytm_details><ytm_details><profile_desc>GII</profile_desc><time_series_desc>Time series - 5 YEARS</time_series_desc><ytm>2.692</ytm></ytm_details><ytm_details><profile_desc>GII</profile_desc><time_series_desc>Time series - 7 YEARS</time_series_desc><ytm>2.770</ytm></ytm_details><ytm_details><profile_desc>GII</profile_desc><time_series_desc>Time series - 8 YEARS</time_series_desc><ytm>2.814</ytm></ytm_details><ytm_details><profile_desc>GII</profile_desc><time_series_desc>Time series - 9 YEARS</time_series_desc><ytm>2.849</ytm></ytm_details><ytm_details><profile_desc>GII</profile_desc><time_series_desc>Time series - 10 YEARS</time_series_desc><ytm>2.882</ytm></ytm_details><ytm_details><profile_desc>GII</profile_desc><time_series_desc>Time series - 15 YEARS</time_series_desc><ytm>3.076</ytm></ytm_details><ytm_details><profile_desc>GII</profile_desc><time_series_desc>Time series - 20 YEARS</time_series_desc><ytm>3.198</ytm></ytm_details><ytm_details><profile_desc>MITB</profile_desc><time_series_desc>Time series - BAND 1</time_series_desc><ytm>2.540</ytm></ytm_details><ytm_details><profile_desc>MITB</profile_desc><time_series_desc>Time series - BAND 10</time_series_desc><ytm>2.597</ytm></ytm_details><ytm_details><profile_desc>MITB</profile_desc><time_series_desc>Time series - BAND 4</time_series_desc><ytm>2.544</ytm></ytm_details><ytm_details><profile_desc>MITB</profile_desc><time_series_desc>Time series - BAND 7</time_series_desc><ytm>2.563</ytm></ytm_details></ytm></YTMResult>